sinkhorn_transformer/__init__.py
sinkhorn_transformer/autopadder.py
sinkhorn_transformer/autoregressive_wrapper.py
sinkhorn_transformer/reversible.py
sinkhorn_transformer/sinkhorn_transformer.py
sinkhorn_transformer-0.11.4.dist-info/LICENSE
sinkhorn_transformer-0.11.4.dist-info/METADATA
sinkhorn_transformer-0.11.4.dist-info/WHEEL
sinkhorn_transformer-0.11.4.dist-info/top_level.txt
sinkhorn_transformer-0.11.4.dist-info/RECORD
