Metadata-Version: 2.1
Name: sinkhorn-transformer
Version: 0.11.4
Summary: Sinkhorn Transformer - Sparse Sinkhorn Attention
Home-page: https://github.com/lucidrains/sinkhorn-transformer
Author: Phil Wang
Author-email: lucidrains@gmail.com
License: MIT
Keywords: transformers,attention,artificial intelligence
Platform: UNKNOWN
Classifier: Development Status :: 4 - Beta
Classifier: Intended Audience :: Developers
Classifier: Topic :: Scientific/Engineering :: Artificial Intelligence
Classifier: License :: OSI Approved :: MIT License
Classifier: Programming Language :: Python :: 3.6
Requires-Dist: axial-positional-embedding (>=0.1.0)
Requires-Dist: local-attention
Requires-Dist: product-key-memory
Requires-Dist: torch
